Workbook

Sheet Checklist
A1: Client details | B1: Please fill yellow colored cells
A2: Client name
A3: Type of integration | B3: Direct integration with client
A4: API product (Select in subsequent column for multiple products)
B5: API Score | C5: =IFERROR(VLOOKUP($C4,'API risk score'!$A:$B,2,0),0) -> 0 | D5: =IFERROR(VLOOKUP(D4,'API risk score'!A:B,2,0),0) -> 0 | E5: =IFERROR(VLOOKUP(E4,'API risk score'!A:B,2,0),0) -> 0 | F5: =IFERROR(VLOOKUP(F4,'API risk score'!A:B,2,0),0) -> 0 | G5: =IFERROR(VLOOKUP(G4,'API risk score'!A:B,2,0),0) -> 0
B6: API risk | C6: =MAX(C5:G5) -> 0 | D6: =IF(AND(C6>0,C6<=35),"Low",IF(AND(C6>35,C6<=70),"Medium",IF(C6>70,"High",0))) -> 0
A7: Approval matrix to be followed | B7: =IF(AND(C13="OTO - Marketplace/ agg",AND(OR(D6="Low",D6="Medium"),OR(D9="Low",D9="Medium"))),"Type 2",IF(AND(OR(D6="Low",D6="Medium"),OR(D9="Low",D9="Medium")),"Type 1",IF(OR(D6="High",D9="High"),"Type 3",0))) -> 0 | C7: Note: Please check sheet Approval Matrix
A8: Client assessment score:
A9: Integrator score | B9: =SUM(D18:D21) -> 0 | D9: =IF(AND(B9>=0,B9<=30),"Low",IF(AND(B9>30,B9<=70),"Medium",IF(B9>70,"High",0))) -> Low
A10: ISG score | B10: =SUM(D22:D23) -> 0 | D10: =IF(AND(B10>0,B10<=20),"Low",IF(B10>20,"High",0)) -> 0
A12: Domain | B12: Checklist | C12: Please select | D12: Remark
A13: Business assessment | B13: Type of Business | E13: Note: Please write in remarks in case of others
B14: Business use case (Please write business use case)
B15: - Average Transactions volume per Day/Month/Quarter/Year - Average Transaction Value per Day/Month/Quarter/Year What is the projected Transaction value and volume per Day?
B16: Is integrator using term "Bank" as suffix in your brand name
B17: Is integrator having existing relationaship with other financial institution?
A18: Technology and Security | B18: The Integrator has certifications for IT infrastructure (ISO 27001 / ISO IEC 20000-1 / others) or they are using standard cloud-based systems such as AWS | D18: =IF(C18="No",30,0) -> 0
B19: The Integrator has a disaster recovery system for its IT system | D19: =IF(C19="No",20,0) -> 0
B20: Is the disaster recovery system based within India | D20: =IF(C20="No",20,0) -> 0
B21: The Integrator has means to implement necessary security, data protection or privacy controls (encryption technology, Firewall, etc.) | D21: =IF(C21="No",30,0) -> 0
A22: ISG | B22: Server is on cloud or inhouse | D22: =IF(C22="In house",5,0) -> 0
B23: Client server is hosted in which geography? (India or Other) | D23: =IF(C23="Outside India",5,0) -> 0
B24: Is SOP in place for identified assets for business criticality and operational continuity? | C24: Not applicable for direct customer integration
B25: Is the process defined for secure disposal or re-use of assets by vendor / CSP
B26: Does the CSP/ Inhouse server has documented and tested Business Continuity (BCP) and Disaster Recovery Plan (DRP) available? If Yes, kindly mention the location where the Banks data would be stored?
B27: Are the security controls in place to segregate the bank data from other tenants’ data if Bank's data is being stored in shared environment?
B28: Is critical data stored in encrypted format along with one way hashing?
B29: What is the retention time for storage of data which is required for legal, regulatory, and business requirements?
B30: Is there SOP in place for secured deletion/purging of all information / data from CSP environment?
B31: Does the CSP has Next generation Firewall for inspection and layer 7 security controls for east west and north south traffic
A32: Legal and regulatory assessment | B32: Has the firm received notice from any regulatory body in the last 5 years
B33: Any major litigations in Police / Court / DRT / Income Tax / ED / CBI / Labour Court or any such regulatory body
A34: Brand Assesment | B34: Will there be any use of ICICI name for branding/marketing purposes?
B35: If yes for above, whether approval from ICICI Bank has been taken or not?
B36: Brand permission letter signed or not for usage of I man logo

Sheet Approval Matrix
A1: Approval matrix | B1: Type 1 | C1: Type 2 | D1: Type 3
A2: To | B2: MES RH | C2: MES ZH | D2: MES ZH
A4: Through | B4: MES RHS | C4: MES RH, MES RHS | D4: MES RH,MES RHS, ISG, ORMG
A6: For info | B6: ORMG, ISG, Compliance, IPM, Brand | C6: ORMG, ISG, Compliance, IPM, Brand | D6: Compliance, IPM, Brand
B8: ORMG (Venkatanarayana) | C8: 269785
B9: ISG (Sudhir Dalvi) | C9: 458926
B10: Brand (Sachin Shukla) | C10: 168521
B11: Compliance (Nilesh Iskande) | C11: 843499
B12: Respective IPM( implementation product manager)
B14: Please attach filled Checklist and API application form in iprocess
A17: Update Date | B17: 46104
A18: Version | B18: V15

Sheet API Risk score1
A1: S.No. | B1: Risk Area | C1: Checklist | D1: Applicability of Checklist | G1: Scoring Criteria | H1: API
D2: Internal APIs | E2: External Published | F2: External Consumed | H2: BBPS | I2: ENACH | J2: CIB API | K2: CIB bulk API | L2: UPI | M2: Composite | N2: IMPS | O2: TAX | P2: GST | Q2: eCollections | R2: I-Sure Pay | S2: H2H | T2: Transaction Alert
A3: 1 | B3: Information / Data Shared | C3: Does the API handle any customer specific information? | G3: 1. Non-encrypted Customer data -15 2. Encrypted Customer data -7.5 3. Non-customer data - 0 | H3: 7.5 | I3: 7.5 | J3: 7.5 | K3: 7.5 | L3: 7.5 | M3: 7.5 | N3: 7.5 | O3: 7.5 | P3: 7.5 | Q3: 7.5 | R3: 7.5 | S3: 7.5 | T3: 7.5
A4: 2 | C4: Does the API handle any personally identifiable information (PII)? | G4: 1. Non-encrypted Customer data -15 2. Encrypted Customer data -7.5 3. Non-customer data - 0 | H4: 7.5 | I4: 7.5 | J4: 7.5 | K4: 7.5 | L4: 7.5 | M4: 7.5 | N4: 7.5 | O4: 7.5 | P4: 7.5 | Q4: 7.5 | R4: 7.5 | S4: 7.5 | T4: 7.5
A5: 3 | B5: Type of Transaction | C5: Is the API meant for financial transaction? | G5: 1. Non-encrypted financial transaction API -20 2. Encrypted financial transaction API -10 3. Non-financial transactional API -0 | H5: 10 | I5: 10 | J5: 10 | K5: 10 | L5: 10 | M5: 10 | N5: 10 | O5: 10 | P5: 10 | Q5: 0 | R5: 10 | S5: 10 | T5: 0
A6: 4 | C6: Will the API allow bulk data transfer? | G6: 1. Yes -10 2. No -0 | H6: 0 | I6: 0 | J6: 0 | K6: 10 | L6: 0 | M6: 0 | N6: 0 | O6: 0 | P6: 0 | Q6: 0 | R6: 0 | S6: 10 | T6: 0
A7: 5 | B7: Security | C7: What is the encryption protocol used for the API? | G7: 1. HTTPS TLS 1.2 -0 2. Any other -20 | H7: 0 | I7: 0 | J7: 0 | K7: 0 | L7: 0 | M7: 0 | N7: 0 | O7: 0 | P7: 0 | Q7: 0 | R7: 0 | S7: 0 | T7: 0
A8: 6 | B8: Business impact* | C8: Does the API have direct impact to revenue or cost for the Bank? | G8: 1. Revenue or cost -15 2. Neither -0 | H8: 15 | I8: 15 | J8: 15 | K8: 15 | L8: 15 | M8: 15 | N8: 15 | O8: 15 | P8: 15 | Q8: 15 | R8: 15 | S8: 15 | T8: 15
H9: =SUM(H3:H8) -> 40 | I9: =SUM(I3:I8) -> 40 | J9: =SUM(J3:J8) -> 40 | K9: =SUM(K3:K8) -> 50 | L9: =SUM(L3:L8) -> 40 | M9: =SUM(M3:M8) -> 40 | N9: =SUM(N3:N8) -> 40 | O9: =SUM(O3:O8) -> 40 | ... T9: =SUM(T3:T8) -> 30

Sheet API risk score
A1: API | B1: Score
A2: CIB Single payment API | B2: 40 | C2: Medium | F2: e-Commerce
A3: CIB Bulk API | B3: 50 | C3: Medium | F3: Manufacturing
A4: UPI Collection | B4: 40 | C4: Medium | F4: Services
A5: Composite Pay | B5: 40 | C5: Medium | F5: Large corporate having Dealer collection model
A6: TAX API | B6: 40 | C6: Medium | F6: Finance/ NBFC
A7: eCollection | B7: 30 | C7: Low | F7: Small & Mid-Size corporates
A8: iSurepay | B8: 40 | C8: Medium | F8: IT/ ITES
A9: H2H Flick | B9: 50 | C9: Medium | F9: Others
A10: Transaction alert API | B10: 30 | C10: Low | F10: OTO - Marketplace/ agg
A11: BBPS | B11: 40 | C11: Medium
A12: eNACH | B12: 40 | C12: Medium
A13: IMPS (Penny Drop) | B13: 40 | C13: Medium
